CHANGES.txt
LICENSE.txt
MANIFEST.in
README.txt
TODO.txt
bootstrap.py
buildout.cfg
setup.py
src/p01/__init__.py
src/p01.build.egg-info/PKG-INFO
src/p01.build.egg-info/SOURCES.txt
src/p01.build.egg-info/dependency_links.txt
src/p01.build.egg-info/entry_points.txt
src/p01.build.egg-info/namespace_packages.txt
src/p01.build.egg-info/not-zip-safe
src/p01.build.egg-info/requires.txt
src/p01.build.egg-info/top_level.txt
src/p01/build/README.txt
src/p01/build/__init__.py
src/p01/build/base.py
src/p01/build/build.py
src/p01/build/deploy.py
src/p01/build/index.txt
src/p01/build/package.py
src/p01/build/tests/__init__.py
src/p01/build/tests/checker.txt
src/p01/build/tests/parse_version.txt
src/p01/build/tests/tests.py